evsauto/__init__.py
evsauto/browserautomation.py
evsauto/config.py
evsauto/spreadsheet.py
evsauto/utils.py
evsauto-0.0.2.dist-info/LICENSE
evsauto-0.0.2.dist-info/METADATA
evsauto-0.0.2.dist-info/WHEEL
evsauto-0.0.2.dist-info/top_level.txt
evsauto-0.0.2.dist-info/RECORD
