Metadata-Version: 2.1
Name: evsauto
Version: 0.0.2
Summary: Everett's personal collection of wrappers/drivers for python-based automation projects.
Author-email: Everett Daniels-Wright <business@everettdw.com>
Project-URL: Homepage, https://github.com/everettadw/evsauto
Classifier: License :: OSI Approved :: MIT License
Classifier: Programming Language :: Python :: 3
Requires-Python: >=3.10
License-File: LICENSE
Requires-Dist: selenium >=4.0.0
Requires-Dist: webdriver-manager >=4.0.0
Requires-Dist: openpyxl >=3.1.0
Requires-Dist: tomlkit >=0.12.0
